pandas_validator/__init__.py
pandas_validator/core/__init__.py
pandas_validator/core/exceptions.py
pandas_validator/validators/__init__.py
pandas_validator/validators/columns.py
pandas_validator/validators/dataframe.py
pandas_validator/validators/index.py
pandas_validator/validators/series.py
pandas_validator/validators/test/__init__.py
pandas_validator/validators/test/test_columns.py
pandas_validator/validators/test/test_dataframe.py
pandas_validator/validators/test/test_index.py
pandas_validator/validators/test/test_series.py
pandas_validator-0.5.0.dist-info/DESCRIPTION.rst
pandas_validator-0.5.0.dist-info/METADATA
pandas_validator-0.5.0.dist-info/metadata.json
pandas_validator-0.5.0.dist-info/RECORD
pandas_validator-0.5.0.dist-info/top_level.txt
pandas_validator-0.5.0.dist-info/WHEEL
