Metadata-Version: 2.0
Name: pandas-validator
Version: 0.5.0
Summary: Validate the pandas objects such as DataFrame and Series.
Home-page: https://github.com/c-bata/pandas-validator
Author: Masashi Shibata <contact@c-bata.link>
Author-email: contact@c-bata.link
License: MIT License
Keywords: pandas validator
Platform: UNKNOWN
Requires-Dist: pandas
